pytiqs/__init__.py
pytiqs/__version__.py
pytiqs/connect.py
pytiqs/constants.py
pytiqs/exceptions.py
pytiqs/sockets.py
pytiqs-1.1.0.dist-info/METADATA
pytiqs-1.1.0.dist-info/WHEEL
pytiqs-1.1.0.dist-info/top_level.txt
pytiqs-1.1.0.dist-info/RECORD
